scons_tool_cxxtestgen-0.2.0-py3.8-nspkg.pth
sconstool/cxxtestgen/__init__.py
sconstool/cxxtestgen/about.py
sconstool/cxxtestgen/detail_.py
scons_tool_cxxtestgen-0.2.0.dist-info/METADATA
scons_tool_cxxtestgen-0.2.0.dist-info/WHEEL
scons_tool_cxxtestgen-0.2.0.dist-info/namespace_packages.txt
scons_tool_cxxtestgen-0.2.0.dist-info/top_level.txt
scons_tool_cxxtestgen-0.2.0.dist-info/RECORD
