Metadata-Version: 2.1
Name: scons-tool-cxxtestgen
Version: 0.2.0
Summary: SCons tool for cxxtestgen command
Home-page: https://github.com/ptomulik/scons-tool-cxxtestgen
Author: Paweł Tomulik
Author-email: ptomulik@meil.pw.edu.pl
License: UNKNOWN
Platform: UNKNOWN
Requires-Python: >=2.7
Requires-Dist: scons-tool-util (>=0.1.8)
